pip_plugin_collection.py
pip_plugin_collection-0.0.1.dist-info/METADATA
pip_plugin_collection-0.0.1.dist-info/RECORD
pip_plugin_collection-0.0.1.dist-info/WHEEL
pip_plugin_collection-0.0.1.dist-info/entry_points.txt
pip_plugin_collection-0.0.1.dist-info/top_level.txt
