Metadata-Version: 2.1
Name: pip-plugin-collection
Version: 0.0.1
Summary: A pip plugin for pip-upgrader.
Home-page: https://github.com/pycampers/pip-plugin-collection
Author: Dev Aggarwal
Author-email: devxpy@gmail.com
License: MIT
Platform: UNKNOWN
Classifier: License :: OSI Approved :: MIT License
Classifier: Programming Language :: Python
Classifier: Programming Language :: Python :: 3
Classifier: Programming Language :: Python :: 3.6
Classifier: Programming Language :: Python :: Implementation :: CPython
Classifier: Programming Language :: Python :: Implementation :: PyPy
Requires-Python: >=3.6.0
Requires-Dist: plugingen
Requires-Dist: pip-upgrader
Requires-Dist: pip-tools
Requires-Dist: pipdeptree
